yta_stock/__init__.py
yta_stock-0.0.1.dist-info/licenses/LICENSE
yta_stock-0.0.1.dist-info/METADATA
yta_stock-0.0.1.dist-info/WHEEL
yta_stock-0.0.1.dist-info/RECORD
