Metadata-Version: 2.4
Name: yta-stock
Version: 0.0.1
Summary: Youtube Autonomous Stock module
License-File: LICENSE
Author: danialcala94
Author-email: danielalcalavalera@gmail.com
Requires-Python: ==3.9
Classifier: Programming Language :: Python :: 3
Classifier: Programming Language :: Python :: 3.9
Requires-Dist: yta_constants (>=0.0.1,<1.0.0)
Requires-Dist: yta_programming (>=0.0.1,<1.0.0)
Requires-Dist: yta_stock_pexels (>=0.0.1,<1.0.0)
Requires-Dist: yta_stock_pixabay (>=0.0.1,<1.0.0)
